{
    "prepare_queue": {
        "installed": [],
        "uninstalled": []
    },
    "config_munge": {
        "files": {
            "Properties/WMAppManifest.xml": {
                "parents": {
                    "/Deployment/App/Capabilities": [
                        {
                            "xml": "<Capability Name=\"ID_CAP_NETWORKING\" />",
                            "count": 2
                        }
                    ]
                }
            },
            "config.xml": {
                "parents": {
                    "/*": [
                        {
                            "xml": "<feature name=\"InAppBrowser\"><param name=\"wp-package\" value=\"InAppBrowser\" /></feature>",
                            "count": 1
                        }
                    ]
                }
            }
        }
    },
    "installed_plugins": {
        "cordova-plugin-inappbrowser": {
            "PACKAGE_NAME": "{5376dc20-071e-11e5-84bb-bd2d264b478b}"
        }
    },
    "dependent_plugins": {}
}